mdexport/__init__.py
mdexport/cli.py
mdexport/config.py
mdexport/core.py
mdexport/exporter.py
mdexport/markdown.py
mdexport/mdexport.py
mdexport/templates.py
mdexport-0.9.2.dist-info/LICENSE
mdexport-0.9.2.dist-info/METADATA
mdexport-0.9.2.dist-info/WHEEL
mdexport-0.9.2.dist-info/entry_points.txt
mdexport-0.9.2.dist-info/RECORD
