Metadata-Version: 2.1
Name: mdexport
Version: 0.9.2
Summary: CLI tool to export markdown to pdf using jinja2 templates.
Author: andyverstraeten
Author-email: andy.verstraeten@gmail.com
Requires-Python: >=3.10,<4.0
Classifier: Programming Language :: Python :: 3
Classifier: Programming Language :: Python :: 3.10
Classifier: Programming Language :: Python :: 3.11
Classifier: Programming Language :: Python :: 3.12
Classifier: Programming Language :: Python :: 3.13
Requires-Dist: beautifulsoup4 (>=4.12.3,<5.0.0)
Requires-Dist: click (>=8.1.7,<9.0.0)
Requires-Dist: jinja2 (>=3.1.4,<4.0.0)
Requires-Dist: markdown2 (>=2.5.1,<3.0.0)
Requires-Dist: python-frontmatter (>=1.1.0,<2.0.0)
Requires-Dist: weasyprint (>=63.0,<64.0)
